MANIFEST.in
README.md
setup.cfg
setup.py
qctoolkit/__init__.py
qctoolkit/back.README.md
qctoolkit/molecule.py
qctoolkit/setting.py
qctoolkit.egg-info/PKG-INFO
qctoolkit.egg-info/SOURCES.txt
qctoolkit.egg-info/dependency_links.txt
qctoolkit.egg-info/requires.txt
qctoolkit.egg-info/top_level.txt
qctoolkit/DB/__init__.py
qctoolkit/DB/logger.py
qctoolkit/MD/__init__.py
qctoolkit/MD/aimd_io.py
qctoolkit/MD/general_io.py
qctoolkit/MD/mdInterface.py
qctoolkit/MD/c_extension/dlist1.c
qctoolkit/MD/c_extension/dlist2.c
qctoolkit/MD/c_extension/vacf.c
qctoolkit/MD/mdcode/__init__.py
qctoolkit/MD/mdcode/cpmd.py
qctoolkit/MD/trajectory/__init__.py
qctoolkit/MD/trajectory/trajectory.py
qctoolkit/MD/trajectory/xyz.py
qctoolkit/ML/README.md
qctoolkit/ML/__init__.py
qctoolkit/ML/dataset.py
qctoolkit/ML/descriptors.py
qctoolkit/ML/kernels.py
qctoolkit/ML/neuralnetworks.py
qctoolkit/ML/tools.py
qctoolkit/ML/c_extension/coulombmatrixmodule.c
qctoolkit/ML/c_extension/kernelmatrixmodule.c
qctoolkit/ML/c_extension/kernels.c
qctoolkit/ML/c_extension/kernels.h
qctoolkit/ML/c_extension/kernels_capi.h
qctoolkit/ML/c_extension/kernelvectorsmodule.c
qctoolkit/ML/c_extension/utilities.c
qctoolkit/ML/c_extension/utilities.h
qctoolkit/ML/wavelet/__init__.py
qctoolkit/ML/wavelet/scattering_transform.py
qctoolkit/QM/__init__.py
qctoolkit/QM/gaussianbasis_io.py
qctoolkit/QM/general_io.py
qctoolkit/QM/planewave_io.py
qctoolkit/QM/qmInterface.py
qctoolkit/QM/qmjob.py
qctoolkit/QM/qmresult.py
qctoolkit/QM/universal.py
qctoolkit/QM/wavelet_io.py
qctoolkit/QM/c_extension/eeint.c
qctoolkit/QM/c_extension/eekernel.c
qctoolkit/QM/c_extension/gaussian.c
qctoolkit/QM/c_extension/gaussian.h
qctoolkit/QM/c_extension/keint.c
qctoolkit/QM/c_extension/knint.c
qctoolkit/QM/c_extension/neint.c
qctoolkit/QM/c_extension/nnint.c
qctoolkit/QM/c_extension/veint.c
qctoolkit/QM/c_extension/vnint.c
qctoolkit/QM/ofdft/__init__.py
qctoolkit/QM/ofdft/cube.py
qctoolkit/QM/ofdft/evaluation.py
qctoolkit/QM/ofdft/grid_points.py
qctoolkit/QM/ofdft/libxc_dict.py
qctoolkit/QM/ofdft/libxc_interface.py
qctoolkit/QM/ofdft/main.py
qctoolkit/QM/ofdft/c_extension/libxc_exc.c
