Metadata-Version: 1.0
Name: qctoolkit
Version: 0.0.14
Summary: quantum chemistry tool kit
Home-page: https://github.com/SamKChang/qctoolkit.git
Author: K. Y. S. Chang
Author-email: ky.sam.chang@gmail.com
License: UNKNOWN
Keywords: quantum,chemistry,wrapper,tools,alchemy,cpmd,quantumespresso,nwchem,bigdft
Platform: UNKNOWN
